FOX/__init__.py
FOX/__version__.py
FOX/entry_points.py
FOX/logger.py
FOX/py.typed
FOX/testing_utils.py
FOX/type_alias.py
FOX/type_alias.pyi
FOX/type_hints.py
FOX/utils.py
FOX/armc/__init__.py
FOX/armc/armc.py
FOX/armc/armc_pt.py
FOX/armc/err_funcs.py
FOX/armc/guess.py
FOX/armc/mc_post_process.py
FOX/armc/monte_carlo.py
FOX/armc/package_manager.py
FOX/armc/param_mapping.py
FOX/armc/phi_updater.py
FOX/armc/run_armc.py
FOX/armc/sanitization.py
FOX/armc/schemas.py
FOX/classes/__init__.py
FOX/classes/multi_mol.py
FOX/classes/multi_mol_magic.py
FOX/data/Cd68Se55_26COO_MD_trajec.xyz
FOX/data/__init__.py
FOX/data/scattering.yaml
FOX/data/shannon_radii.csv
FOX/data/uff.csv
FOX/examples/__init__.py
FOX/examples/cp2k_armc.py
FOX/examples/input.py
FOX/ff/__init__.py
FOX/ff/bonded_calculate.py
FOX/ff/degree_of_separation.py
FOX/ff/lj_calculate.py
FOX/ff/lj_dataframe.py
FOX/ff/lj_intra_calculate.py
FOX/ff/lj_param.py
FOX/ff/lj_uff.py
FOX/ff/parse_wildcards.py
FOX/ff/shannon_radii.py
FOX/functions/__init__.py
FOX/functions/adf.py
FOX/functions/charge_parser.py
FOX/functions/charge_utils.py
FOX/functions/cp2k_utils.py
FOX/functions/debye.py
FOX/functions/molecule_utils.py
FOX/functions/periodic.py
FOX/functions/randomize_param.py
FOX/functions/rdf.py
FOX/functions/sorting.py
FOX/io/__init__.py
FOX/io/cp2k.py
FOX/io/cp2k_to_prm.py
FOX/io/hdf5_utils.py
FOX/io/read_kf.py
FOX/io/read_prm.py
FOX/io/read_psf.py
FOX/io/read_xyz.py
FOX/properties/__init__.py
FOX/properties/base.py
FOX/properties/base.pyi
FOX/properties/bulk_modulus.py
FOX/properties/pressure.py
FOX/recipes/__init__.py
FOX/recipes/histogram.py
FOX/recipes/ligands.py
FOX/recipes/param.py
FOX/recipes/psf.py
FOX/recipes/similarity.py
FOX/recipes/similarity.pyi
FOX/recipes/time_resolution.py
Auto_FOX-0.10.2.dist-info/LICENSE
Auto_FOX-0.10.2.dist-info/METADATA
Auto_FOX-0.10.2.dist-info/WHEEL
Auto_FOX-0.10.2.dist-info/entry_points.txt
Auto_FOX-0.10.2.dist-info/top_level.txt
Auto_FOX-0.10.2.dist-info/RECORD
