Metadata-Version: 2.1
Name: Auto-FOX
Version: 0.10.2
Summary: A library for analyzing potential energy surfaces (PESs) and using the resulting PES descriptors for constructing forcefield parameters.
Home-page: https://github.com/nlesc-nano/Auto-FOX
Author: Bas van Beek
Author-email: b.f.van.beek@vu.nl
License: GNU General Public License v3 or later
Keywords: quantum-mechanics,molecular-mechanics,science,chemistry,forcefield-parameterization,forcefield,python-3,python-3.7,python-3.8,python-3.9,python-3.10
Classifier: Development Status :: 4 - Beta
Classifier: Intended Audience :: Science/Research
Classifier: License :: OSI Approved :: GNU General Public License v3 or later (GPLv3+)
Classifier: Natural Language :: English
Classifier: Operating System :: Unix
Classifier: Operating System :: MacOS
Classifier: Programming Language :: Python
Classifier: Programming Language :: Python :: 3
Classifier: Programming Language :: Python :: 3.7
Classifier: Programming Language :: Python :: 3.8
Classifier: Programming Language :: Python :: 3.9
Classifier: Programming Language :: Python :: 3.10
Classifier: Topic :: Scientific/Engineering :: Chemistry
Classifier: Topic :: Software Development :: Libraries 
Classifier: Typing :: Typed
Requires-Python: >=3.7
License-File: LICENSE
Requires-Dist: Nano-Utils (>=2.3)
Requires-Dist: pyyaml (>=5.1)
Requires-Dist: numpy (>=1.17)
Requires-Dist: scipy (>=1.2)
Requires-Dist: pandas (>=0.24)
Requires-Dist: schema (!=0.7.5,>=0.7.1)
Requires-Dist: AssertionLib (>=2.3)
Requires-Dist: noodles (>=0.3.3)
Requires-Dist: h5py (>=2.10)
Requires-Dist: qmflows (>=0.11.0)
Requires-Dist: plams (>=1.5.1)
Provides-Extra: docs
Requires-Dist: sphinx (>=2.4) ; extra == 'docs'
Requires-Dist: sphinx-rtd-theme (>=0.3.0) ; extra == 'docs'
Requires-Dist: matplotlib (>=3.0) ; extra == 'docs'
Provides-Extra: test
Requires-Dist: ase (>=3.21.1) ; extra == 'test'
Requires-Dist: nlesc-CAT (>=0.10.0) ; extra == 'test'
Requires-Dist: pytest (>=5.4.0) ; extra == 'test'
Requires-Dist: pytest-cov ; extra == 'test'
Requires-Dist: sphinx (>=2.4) ; extra == 'test'
Requires-Dist: sphinx-rtd-theme (>=0.3.0) ; extra == 'test'
Requires-Dist: matplotlib (>=3.0) ; extra == 'test'
Provides-Extra: test_no_optional
Requires-Dist: pytest (>=5.4.0) ; extra == 'test_no_optional'
Requires-Dist: pytest-cov ; extra == 'test_no_optional'
